{"is_source_file": true, "format": "Dart", "description": "Main entry point and core source file for a Flutter-based bookstore transaction management app, containing implementations of API client, data models, providers for authentication and transactions, and UI screens including login, dashboard, transaction form, and profile.", "external_files": ["dart:convert", "package:flutter/material.dart", "package:flutter_dotenv/flutter_dotenv.dart", "package:provider/provider.dart", "package:shared_preferences/shared_preferences.dart", "package:http/http.dart"], "external_methods": ["jsonEncode", "jsonDecode", "SharedPreferences.getString", "SharedPreferences.setString", "SharedPreferences.remove", "http.post", "http.get", "http.put", "http.delete", "showDatePicker", "Navigator.of", "runApp", "WidgetsFlutterBinding.ensureInitialized"], "published": ["main", "ApiClient", "TransactionModel", "AuthProvider", "TransactionsProvider", "BookstoreApp", "RootGate", "MainScaffold", "LoginScreen", "DashboardScreen", "ProfileScreen", "TransactionFormScreen"], "classes": [{"name": "ApiClient", "description": "A client for making authenticated API requests, reading base URL from environment variables, and including JWT tokens in headers if available."}, {"name": "TransactionModel", "description": "Data model representing a bookstore transaction with JSON serialization and copying features."}, {"name": "AuthProvider", "description": "Manages user authentication state, persists JWT tokens and username, and provides login/logout methods."}, {"name": "TransactionsProvider", "description": "Manages loading, creating, updating, and deleting transaction records through backend API."}, {"name": "BookstoreApp", "description": "Root widget configuring theme and starting the app with providers."}, {"name": "RootGate", "description": "Determines whether to show login or main interface based on authentication status."}, {"name": "MainScaffold", "description": "Main app scaffold with bottom navigation and page routing."}, {"name": "LoginScreen", "description": "UI screen for user login with input validation and state management."}, {"name": "DashboardScreen", "description": "Displays summary of transactions and list with options to edit or delete."}, {"name": "ProfileScreen", "description": "Shows user profile info with sign out option."}, {"name": "TransactionFormScreen", "description": "Form for creating or editing transactions, with date picker and validation."}], "methods": [{"name": "main", "description": "Application entry point, loads environment, initializes shared preferences and providers, and runs the app."}, {"name": "ApiClient", "description": "Constructor and methods for forming HTTP requests with authentication."}, {"name": "TransactionModel.fromJson", "description": "Creates a TransactionModel from JSON data."}, {"name": "TransactionModel.toJson", "description": "Converts a TransactionModel instance into JSON."}, {"name": "AuthProvider.login", "description": "Performs user login, stores JWT token and username upon success."}, {"name": "AuthProvider.logout", "description": "Clears stored JWT token and username."}, {"name": "TransactionsProvider.fetchAll", "description": "Loads all transactions from backend API."}, {"name": "TransactionsProvider.create", "description": "Creates a new transaction."}, {"name": "TransactionsProvider.update", "description": "Updates an existing transaction."}, {"name": "TransactionsProvider.remove", "description": "Deletes a transaction."}], "calls": ["dotenv.load", "SharedPreferences.getInstance", "runApp", "MultiProvider", "ChangeNotifierProvider", "WidgetsFlutterBinding.ensureInitialized", "MaterialApp", "Navigator.of", "setState", "context.select", "context.read", "context.watch", "ScaffoldMessenger.of", "showDatePicker", "jsonEncode", "jsonDecode", "http.post", "http.get", "http.put", "http.delete"], "search-terms": ["ApiClient", "TransactionModel", "AuthProvider", "TransactionsProvider", "Flutter", "environment variables", "SharedPreferences", "http client", "transaction management", "Flutter app", "UI screens", "login", "dashboard", "transaction form", "profile"], "state": 2, "file_id": 16, "knowledge_revision": 43, "git_revision": "", "revision_history": [{"37": ""}, {"38": ""}, {"43": ""}], "hash": "ec266748349e52f04865bb6fb539f1a9", "format-version": 4, "code-base-name": "bookstore_frontend", "filename": "bookstore_frontend/lib/main.dart"}